OmieAPI/__init__.py
OmieAPI-0.0.1.dist-info/LICENSE.txt
OmieAPI-0.0.1.dist-info/METADATA
OmieAPI-0.0.1.dist-info/WHEEL
OmieAPI-0.0.1.dist-info/top_level.txt
OmieAPI-0.0.1.dist-info/RECORD
